odoo/addons/shopfloor_checkout_sync/README.rst
odoo/addons/shopfloor_checkout_sync/__init__.py
odoo/addons/shopfloor_checkout_sync/__manifest__.py
odoo/addons/shopfloor_checkout_sync/actions/__init__.py
odoo/addons/shopfloor_checkout_sync/actions/checkout_sync.py
odoo/addons/shopfloor_checkout_sync/i18n/es_AR.po
odoo/addons/shopfloor_checkout_sync/i18n/it.po
odoo/addons/shopfloor_checkout_sync/i18n/shopfloor_checkout_sync.pot
odoo/addons/shopfloor_checkout_sync/readme/CONTRIBUTORS.md
odoo/addons/shopfloor_checkout_sync/readme/CREDITS.md
odoo/addons/shopfloor_checkout_sync/readme/DESCRIPTION.md
odoo/addons/shopfloor_checkout_sync/services/__init__.py
odoo/addons/shopfloor_checkout_sync/services/cluster_picking.py
odoo/addons/shopfloor_checkout_sync/services/location_content_transfer.py
odoo/addons/shopfloor_checkout_sync/services/zone_picking.py
odoo/addons/shopfloor_checkout_sync/static/description/icon.png
odoo/addons/shopfloor_checkout_sync/static/description/index.html
odoo/addons/shopfloor_checkout_sync/tests/__init__.py
odoo/addons/shopfloor_checkout_sync/tests/common.py
odoo/addons/shopfloor_checkout_sync/tests/test_shopfloor_cluster_picking_sync.py
odoo/addons/shopfloor_checkout_sync/tests/test_shopfloor_location_content_transfer_sync.py
odoo/addons/shopfloor_checkout_sync/tests/test_shopfloor_zone_picking_sync.py
odoo_addon_shopfloor_checkout_sync-18.0.1.0.0.1.dist-info/METADATA
odoo_addon_shopfloor_checkout_sync-18.0.1.0.0.1.dist-info/WHEEL
odoo_addon_shopfloor_checkout_sync-18.0.1.0.0.1.dist-info/top_level.txt
odoo_addon_shopfloor_checkout_sync-18.0.1.0.0.1.dist-info/RECORD
